z3c/caching/__init__.py
z3c/caching/configure.zcml
z3c/caching/interfaces.py
z3c/caching/lastmodified.py
z3c/caching/meta.zcml
z3c/caching/purge.py
z3c/caching/registry.py
z3c/caching/zcml.py
z3c/caching/tests/__init__.py
z3c/caching/tests/test1.zcml
z3c/caching/tests/test2.zcml
z3c/caching/tests/test3.zcml
z3c/caching/tests/test4.zcml
z3c/caching/tests/test5.zcml
z3c/caching/tests/test_lastmodified.py
z3c/caching/tests/test_purge.py
z3c/caching/tests/test_registry.py
z3c/caching/tests/test_zcml.py
z3c_caching-4.0.dist-info/LICENSE.txt
z3c_caching-4.0.dist-info/METADATA
z3c_caching-4.0.dist-info/WHEEL
z3c_caching-4.0.dist-info/top_level.txt
z3c_caching-4.0.dist-info/RECORD
