Metadata-Version: 2.2
Name: z3c.caching
Version: 4.0
Summary: Caching infrastructure for web apps
Home-page: https://github.com/zopefoundation/z3c.caching
Author: Wichert Akkerman
Author-email: zope-dev@zope.dev
License: ZPL
Keywords: zope caching
Classifier: Development Status :: 5 - Production/Stable
Classifier: Environment :: Web Environment
Classifier: Intended Audience :: Developers
Classifier: License :: OSI Approved :: Zope Public License
Classifier: Programming Language :: Python :: 3
Classifier: Programming Language :: Python :: 3.9
Classifier: Programming Language :: Python :: 3.10
Classifier: Programming Language :: Python :: 3.11
Classifier: Programming Language :: Python :: 3.12
Classifier: Programming Language :: Python :: 3.13
Classifier: Programming Language :: Python :: Implementation :: CPython
Classifier: Programming Language :: Python :: Implementation :: PyPy
Classifier: Topic :: Software Development :: Libraries :: Python Modules
Requires-Python: >=3.9
License-File: LICENSE.txt
Requires-Dist: setuptools
Requires-Dist: zope.browser
Requires-Dist: zope.component
Requires-Dist: zope.event
Requires-Dist: zope.interface>=3.8.0
Requires-Dist: zope.schema
Requires-Dist: zope.lifecycleevent
Provides-Extra: zcml
Requires-Dist: zope.configuration; extra == "zcml"
Provides-Extra: test
Requires-Dist: zope.configuration; extra == "test"
Dynamic: author
Dynamic: author-email
Dynamic: classifier
Dynamic: description
Dynamic: home-page
Dynamic: keywords
Dynamic: license
Dynamic: provides-extra
Dynamic: requires-dist
Dynamic: requires-python
Dynamic: summary
